TrainHelper/__init__.py
TrainHelper/callbacks/__init__.py
TrainHelper/callbacks/repeater.py
TrainHelper/configuration/__init__.py
TrainHelper/configuration/config.py
TrainHelper/configuration/reader.py
TrainHelper/keras_utils/__init__.py
TrainHelper/keras_utils/keras_functions.py
TrainHelper/queuers/__init__.py
TrainHelper/queuers/console_queuer.py
TrainHelper/queuers/qsub_queuer.py
TrainHelper/queuers/queuer.py
TrainHelper/queuers/slurm_queuer.py
TrainHelper/runners/__init__.py
TrainHelper/runners/base_runner.py
TrainHelper/runners/runner.py
TrainHelper/utils/__init__.py
TrainHelper/utils/functions.py
TrainHelper/utils/queuer.py
TrainHelper/utils/utils.py
TrainHelper-0.0.3.30.dist-info/DESCRIPTION.rst
TrainHelper-0.0.3.30.dist-info/METADATA
TrainHelper-0.0.3.30.dist-info/RECORD
TrainHelper-0.0.3.30.dist-info/WHEEL
TrainHelper-0.0.3.30.dist-info/metadata.json
TrainHelper-0.0.3.30.dist-info/top_level.txt
