Metadata-Version: 2.0
Name: TrainHelper
Version: 0.0.3.30
Summary: UNKNOWN
Home-page: https://github.com/MaLiN2223/TrainHelper
Author: UNKNOWN
Author-email: UNKNOWN
License: MIT
Download-URL: https://github.com/MaLiN2223/TrainHelper/archive/0.1.tar.gz
Platform: UNKNOWN
Requires-Dist: scikit-learn
Requires-Dist: numpy
Requires-Dist: keras
